pyproject_to_setup/__init__.py
pyproject_to_setup/cli.py
pyproject_to_setup/converter.py
pyproject_to_setup/errors.py
pyproject_to_setup/generator.py
pyproject_to_setup/models.py
pyproject_to_setup/validation.py
pyproject_to_setup-0.1.1.dist-info/METADATA
pyproject_to_setup-0.1.1.dist-info/WHEEL
pyproject_to_setup-0.1.1.dist-info/entry_points.txt
pyproject_to_setup-0.1.1.dist-info/licenses/LICENSE
pyproject_to_setup-0.1.1.dist-info/RECORD
