Metadata-Version: 2.4
Name: pyproject-to-setup
Version: 0.1.1
Summary: Convert pyproject.toml to setup.py
Project-URL: Repository, https://github.com/Geson-anko/pyproject-to-setup
Project-URL: Issues, https://github.com/Geson-anko/pyproject-to-setup/issues
Author-email: GesonAnko <59220704+Geson-anko@users.noreply.github.com>
License-File: LICENSE
Keywords: convert,pyproject,pyproject.toml,setup.py,setuptool
Classifier: Development Status :: 3 - Alpha
Classifier: Intended Audience :: Developers
Classifier: License :: OSI Approved :: MIT License
Classifier: Natural Language :: English
Classifier: Natural Language :: Japanese
Classifier: Programming Language :: Python :: 3
Classifier: Programming Language :: Python :: 3.12
Classifier: Programming Language :: Python :: 3.13
Requires-Python: >=3.12
Requires-Dist: click>=8.1.8
